gfs_basic/__init__.py
gfs_basic/Fuzzy_Logic_Toolbox/FuzzyToolbox.py
gfs_basic/Fuzzy_Logic_Toolbox/Initialize_Trees.py
gfs_basic/Fuzzy_Logic_Toolbox/Simple_FISs.py
gfs_basic/Fuzzy_Logic_Toolbox/ViewingTools.py
gfs_basic/Fuzzy_Logic_Toolbox/__init__.py
gfs_basic/Genetic_Algorithm_Toolbox/GeneticAlgorithm.py
gfs_basic/Genetic_Algorithm_Toolbox/RunGA.py
gfs_basic/Genetic_Algorithm_Toolbox/__init__.py
gfs_basic-1.0.1.dist-info/LICENSE
gfs_basic-1.0.1.dist-info/METADATA
gfs_basic-1.0.1.dist-info/WHEEL
gfs_basic-1.0.1.dist-info/top_level.txt
gfs_basic-1.0.1.dist-info/zip-safe
gfs_basic-1.0.1.dist-info/RECORD
